cubicweb_wireit/__init__.py
cubicweb_wireit/__pkginfo__.py
cubicweb_wireit/entities.py
cubicweb_wireit/hooks.py
cubicweb_wireit/schema.py
cubicweb_wireit/setup.py
cubicweb_wireit/data/cw_wiring_editor.css
cubicweb_wireit/data/cw_wiring_editor.js
cubicweb_wireit/data/terminals_file.png
cubicweb_wireit/data/terminals_float.png
cubicweb_wireit/data/terminals_int.png
cubicweb_wireit/data/terminals_string.png
cubicweb_wireit/data/jq_upload/css/jquery.fileupload-ui.css
cubicweb_wireit/data/jq_upload/css/style.css
cubicweb_wireit/data/jq_upload/img/loading.gif
cubicweb_wireit/data/jq_upload/img/progressbar.gif
cubicweb_wireit/data/jq_upload/js/jquery.fileupload-fp.js
cubicweb_wireit/data/jq_upload/js/jquery.fileupload-ui.js
cubicweb_wireit/data/jq_upload/js/jquery.fileupload.js
cubicweb_wireit/data/jq_upload/js/jquery.iframe-transport.js
cubicweb_wireit/data/jq_upload/js/locale.js
cubicweb_wireit/data/jq_upload/js/main.js
cubicweb_wireit/data/jq_upload/js/cors/jquery.postmessage-transport.js
cubicweb_wireit/data/jq_upload/js/cors/jquery.xdr-transport.js
cubicweb_wireit/data/jq_upload/js/vendor/jquery.ui.widget.js
cubicweb_wireit/data/wireit/css/WireIt.css
cubicweb_wireit/data/wireit/css/WireItEditor.css
cubicweb_wireit/data/wireit/images/close.png
cubicweb_wireit/data/wireit/images/cut.png
cubicweb_wireit/data/wireit/images/terminals.png
cubicweb_wireit/data/wireit/images/icons/add.png
cubicweb_wireit/data/wireit/images/icons/application_go.png
cubicweb_wireit/data/wireit/images/icons/bullet_go.png
cubicweb_wireit/data/wireit/images/icons/database_save.png
cubicweb_wireit/data/wireit/images/icons/delete.png
cubicweb_wireit/data/wireit/images/icons/help.png
cubicweb_wireit/data/wireit/js/CanvasElement.js
cubicweb_wireit/data/wireit/js/ImageContainer.js
cubicweb_wireit/data/wireit/js/InOutContainer.js
cubicweb_wireit/data/wireit/js/Layer.js
cubicweb_wireit/data/wireit/js/LayerMap.js
cubicweb_wireit/data/wireit/js/Layout.js
cubicweb_wireit/data/wireit/js/Wire.js
cubicweb_wireit-1.3.0.dist-info/METADATA
cubicweb_wireit-1.3.0.dist-info/WHEEL
cubicweb_wireit-1.3.0.dist-info/entry_points.txt
cubicweb_wireit-1.3.0.dist-info/top_level.txt
cubicweb_wireit-1.3.0.dist-info/RECORD
